smithers.py
smithers_llm-1.0.10.dist-info/METADATA
smithers_llm-1.0.10.dist-info/WHEEL
smithers_llm-1.0.10.dist-info/entry_points.txt
smithers_llm-1.0.10.dist-info/top_level.txt
smithers_llm-1.0.10.dist-info/RECORD
