Metadata-Version: 2.2
Name: smithers-llm
Version: 1.0.10
Summary: An LLM-powered CLI that simulates job interviews based on your resume.
Project-URL: GitHub, https://github.com/Wenceslauu/smithers
Requires-Python: >=3.13
Requires-Dist: langchain-community>=0.3.13
Requires-Dist: langchain>=0.3.13
Requires-Dist: langchain-core>=0.3.28
Requires-Dist: langchain-ollama>=0.2.2
Requires-Dist: langgraph>=0.2.60
Requires-Dist: pypdf>=5.1.0
Requires-Dist: ipykernel>=6.29.5
Requires-Dist: python-dotenv>=1.0.1
Requires-Dist: click>=8.1.8
Requires-Dist: setuptools>=75.8.0
Requires-Dist: httpx>=0.27.2
Requires-Dist: halo>=0.0.31
Requires-Dist: build>=1.2.2.post1
